{
  "name": "X1_Panel",
  "type": "ARM",
  "dependenceList": [],
  "srcDirs": [],
  "virtualFolder": {
    "name": "<virtual_root>",
    "files": [],
    "folders": [
      {
        "name": "Arduino",
        "files": [
          {
            "path": "../Arduino/abi.cpp"
          },
          {
            "path": "../Arduino/itoa.c"
          },
          {
            "path": "../Arduino/Print.cpp"
          },
          {
            "path": "../Arduino/Stream.cpp"
          },
          {
            "path": "../Arduino/WInterrupts.cpp"
          },
          {
            "path": "../Arduino/wiring_analog.cpp"
          },
          {
            "path": "../Arduino/wiring_digital.cpp"
          },
          {
            "path": "../Arduino/wiring_shift.c"
          },
          {
            "path": "../Arduino/WMath.cpp"
          },
          {
            "path": "../Arduino/WString.cpp"
          },
          {
            "path": "../Arduino/yield.c"
          },
          {
            "path": "../Arduino/variants/generic_hc32f460/variant.cpp"
          },
          {
            "path": "../Arduino/avr/dtostrf.c"
          }
        ],
        "folders": [
          {
            "name": "drivers",
            "files": [],
            "folders": [
              {
                "name": "adc",
                "files": [
                  {
                    "path": "../Arduino/drivers/adc/adc.cpp"
                  },
                  {
                    "path": "../Arduino/drivers/adc/adc_config.cpp"
                  }
                ],
                "folders": []
              },
              {
                "name": "gpio",
                "files": [
                  {
                    "path": "../Arduino/drivers/gpio/addon_gpio.c"
                  }
                ],
                "folders": []
              },
              {
                "name": "irqn",
                "files": [
                  {
                    "path": "../Arduino/drivers/irqn/irqn.cpp"
                  }
                ],
                "folders": []
              },
              {
                "name": "panic",
                "files": [
                  {
                    "path": "../Arduino/drivers/panic/ddl_assert.c"
                  },
                  {
                    "path": "../Arduino/drivers/panic/panic.cpp"
                  }
                ],
                "folders": []
              },
              {
                "name": "sysclock",
                "files": [
                  {
                    "path": "../Arduino/drivers/sysclock/sysclock.cpp"
                  },
                  {
                    "path": "../Arduino/drivers/sysclock/sysclock_util.cpp"
                  },
                  {
                    "path": "../Arduino/drivers/sysclock/systick.cpp"
                  }
                ],
                "folders": []
              },
              {
                "name": "timera",
                "files": [
                  {
                    "path": "../Arduino/drivers/timera/timera_config.cpp"
                  }
                ],
                "folders": []
              },
              {
                "name": "usart",
                "files": [
                  {
                    "path": "../Arduino/drivers/usart/Usart.cpp"
                  },
                  {
                    "path": "../Arduino/drivers/usart/usart_config.cpp"
                  },
                  {
                    "path": "../Arduino/drivers/usart/usart_handlers.h"
                  },
                  {
                    "path": "../Arduino/drivers/usart/usart_sync.cpp"
                  }
                ],
                "folders": []
              }
            ]
          },
          {
            "name": "libraries",
            "files": [],
            "folders": []
          }
        ]
      },
      {
        "name": "config",
        "files": [
          {
            "path": "../config/ddl_config.h"
          },
          {
            "path": "../config/mcu_config.h"
          }
        ],
        "folders": []
      },
      {
        "name": "libraries",
        "files": [],
        "folders": [
          {
            "name": "lwmem",
            "files": [
              {
                "path": "../libraries/lwmem/src/lwmem/lwmem.c"
              },
              {
                "path": "../libraries/lwmem/src/lwmem/lwmem.cpp"
              }
            ],
            "folders": []
          },
          {
            "name": "mp2762a",
            "files": [
              {
                "path": "../libraries/Mp2762a/mp2762a.cpp"
              }
            ],
            "folders": []
          },
          {
            "name": "bq40z50",
            "files": [
              {
                "path": "../libraries/Bq40z50/bq40z50.cpp"
              }
            ],
            "folders": []
          }
        ]
      },
      {
        "name": "platfrom",
        "files": [],
        "folders": [
          {
            "name": "core",
            "files": [
              {
                "path": "../platform/core/delay.c"
              },
              {
                "path": "../platform/core/system.c"
              }
            ],
            "folders": []
          },
          {
            "name": "LL_Drivers",
            "files": [
              {
                "path": "../platform/LL_drivers/src/hc32f460_adc.c"
              },
              {
                "path": "../platform/LL_drivers/src/hc32f460_aes.c"
              },
              {
                "path": "../platform/LL_drivers/src/hc32f460_can.c"
              },
              {
                "path": "../platform/LL_drivers/src/hc32f460_clk.c"
              },
              {
                "path": "../platform/LL_drivers/src/hc32f460_cmp.c"
              },
              {
                "path": "../platform/LL_drivers/src/hc32f460_crc.c"
              },
              {
                "path": "../platform/LL_drivers/src/hc32f460_dcu.c"
              },
              {
                "path": "../platform/LL_drivers/src/hc32f460_dmac.c"
              },
              {
                "path": "../platform/LL_drivers/src/hc32f460_efm.c"
              },
              {
                "path": "../platform/LL_drivers/src/hc32f460_emb.c"
              },
              {
                "path": "../platform/LL_drivers/src/hc32f460_event_port.c"
              },
              {
                "path": "../platform/LL_drivers/src/hc32f460_exint_nmi_swi.c"
              },
              {
                "path": "../platform/LL_drivers/src/hc32f460_gpio.c"
              },
              {
                "path": "../platform/LL_drivers/src/hc32f460_hash.c"
              },
              {
                "path": "../platform/LL_drivers/src/hc32f460_i2c.c"
              },
              {
                "path": "../platform/LL_drivers/src/hc32f460_i2s.c"
              },
              {
                "path": "../platform/LL_drivers/src/hc32f460_icg.c"
              },
              {
                "path": "../platform/LL_drivers/src/hc32f460_interrupts.c"
              },
              {
                "path": "../platform/LL_drivers/src/hc32f460_keyscan.c"
              },
              {
                "path": "../platform/LL_drivers/src/hc32f460_mpu.c"
              },
              {
                "path": "../platform/LL_drivers/src/hc32f460_ots.c"
              },
              {
                "path": "../platform/LL_drivers/src/hc32f460_pwc.c"
              },
              {
                "path": "../platform/LL_drivers/src/hc32f460_qspi.c"
              },
              {
                "path": "../platform/LL_drivers/src/hc32f460_rmu.c"
              },
              {
                "path": "../platform/LL_drivers/src/hc32f460_rtc.c"
              },
              {
                "path": "../platform/LL_drivers/src/hc32f460_sdioc.c"
              },
              {
                "path": "../platform/LL_drivers/src/hc32f460_spi.c"
              },
              {
                "path": "../platform/LL_drivers/src/hc32f460_sram.c"
              },
              {
                "path": "../platform/LL_drivers/src/hc32f460_swdt.c"
              },
              {
                "path": "../platform/LL_drivers/src/hc32f460_timer0.c"
              },
              {
                "path": "../platform/LL_drivers/src/hc32f460_timer4_cnt.c"
              },
              {
                "path": "../platform/LL_drivers/src/hc32f460_timer4_emb.c"
              },
              {
                "path": "../platform/LL_drivers/src/hc32f460_timer4_oco.c"
              },
              {
                "path": "../platform/LL_drivers/src/hc32f460_timer4_pwm.c"
              },
              {
                "path": "../platform/LL_drivers/src/hc32f460_timer4_sevt.c"
              },
              {
                "path": "../platform/LL_drivers/src/hc32f460_timer6.c"
              },
              {
                "path": "../platform/LL_drivers/src/hc32f460_timera.c"
              },
              {
                "path": "../platform/LL_drivers/src/hc32f460_trng.c"
              },
              {
                "path": "../platform/LL_drivers/src/hc32f460_usart.c"
              },
              {
                "path": "../platform/LL_drivers/src/hc32f460_utility.c"
              },
              {
                "path": "../platform/LL_drivers/src/hc32f460_wdt.c"
              }
            ],
            "folders": []
          },
          {
            "name": "mcu",
            "files": [
              {
                "path": "../platform/mcu/common/system_hc32f460.c"
              }
            ],
            "folders": []
          },
          {
            "name": "startUp",
            "files": [
              {
                "path": "../platform/startup/startup_hc32f460.S"
              }
            ],
            "folders": []
          },
          {
            "name": "syscalls",
            "files": [
              {
                "path": "../platform/syscalls/newlib.c"
              },
              {
                "path": "../platform/syscalls/syscalls.c"
              },
              {
                "path": "../platform/syscalls/sysmem.c"
              }
            ],
            "folders": []
          }
        ]
      },
      {
        "name": "user",
        "files": [
          {
            "path": "../user/init.cpp"
          },
          {
            "path": "../user/main.cpp"
          }
        ],
        "folders": [
          {
            "name": "src",
            "files": [
              {
                "path": "../user/src/battery.cpp"
              },
              {
                "path": "../user/src/charger_control_new.cpp"
              },
              {
                "path": "../user/src/LCD.cpp"
              },
              {
                "path": "../user/src/led.cpp"
              },
              {
                "path": "../user/src/MYSPI.cpp"
              },
              {
                "path": "../user/src/power_control.cpp"
              }
            ],
            "folders": []
          },
          {
            "name": "inc",
            "files": [
              {
                "path": "../user/inc/battery.h"
              },
              {
                "path": "../user/inc/charger_control_new.h"
              },
              {
                "path": "../user/inc/CommonMacro.h"
              },
              {
                "path": "../user/inc/LCD.h"
              },
              {
                "path": "../user/inc/led.h"
              },
              {
                "path": "../user/inc/logo.h"
              },
              {
                "path": "../user/inc/mcu_define.h"
              },
              {
                "path": "../user/inc/MYSPI.h"
              },
              {
                "path": "../user/inc/power_control.h"
              }
            ],
            "folders": []
          }
        ]
      }
    ]
  },
  "outDir": "build",
  "deviceName": null,
  "packDir": null,
  "miscInfo": {
    "uid": "5b3c8472fc496a9f95b4a3607e2da328"
  },
  "targets": {
    "Debug": {
      "excludeList": [
        "<virtual_root>/platfrom/syscalls/newlib.c"
      ],
      "toolchain": "GCC",
      "compileConfig": {
        "cpuType": "Cortex-M4",
        "archExtensions": "",
        "floatingPointHardware": "single",
        "scatterFilePath": "../platform/startup/linker/hc32f46x_final.ld",
        "useCustomScatterFile": true,
        "storageLayout": {
          "RAM": [],
          "ROM": []
        },
        "options": "null"
      },
      "uploader": "JLink",
      "uploadConfig": {
        "bin": "",
        "baseAddr": "",
        "cpuInfo": {
          "vendor": "XHSC",
          "cpuName": "HC32F460xE"
        },
        "proType": 1,
        "speed": 8000,
        "otherCmds": ""
      },
      "uploadConfigMap": {},
      "custom_dep": {
        "name": "default",
        "incList": [
          "../Arduino",
          "../Arduino/avr",
          "../Arduino/variants/generic_hc32f460",
          "../config",
          "../platform/core",
          "../platform/LL_drivers/inc",
          "../platform/mcu/cmsis",
          "../platform/mcu/common",
          "../user/inc",
          "../user",
          "../libraries/lwmem/src/include",
          "../libraries"
        ],
        "libList": [],
        "defineList": [
          "HC32F460",
          "USE_DEVICE_DRIVER_LIB",
          "__CORE_DEBUG"
        ]
      },
      "builderOptions": {
        "GCC": {
          "version": 5,
          "beforeBuildTasks": [
            {
              "name": "new prebuild task",
              "disable": false,
              "abortAfterFailed": false,
              "stopBuildAfterFailed": true,
              "command": "arm-none-eabi-gcc -C -P -x c -E \"../platform/startup/linker/hc32f46x_param.ld\" -o \"../platform/startup/linker/hc32f46x_final.ld\" -DLD_FLASH_START=0x00000000 -DLD_FLASH_SIZE=0x80000 -DLD_BOOT_MODE=1 -DDDL_STACK_SIZE=0x00001000"
            }
          ],
          "afterBuildTasks": [],
          "global": {
            "$float-abi-type": "hard",
            "output-debug-info": "enable",
            "misc-control": "--specs=nosys.specs --specs=nano.specs"
          },
          "c/cpp-compiler": {
            "language-c": "c11",
            "language-cpp": "c++11",
            "optimization": "level-debug",
            "warnings": "all-warnings",
            "one-elf-section-per-function": true,
            "one-elf-section-per-data": true
          },
          "asm-compiler": {},
          "linker": {
            "$outputTaskExcludes": [
              ".bin"
            ],
            "output-format": "elf",
            "remove-unused-input-sections": true,
            "LIB_FLAGS": "-lm",
            "$toolName": "auto"
          }
        }
      }
    }
  },
  "version": "3.6"
}